{"cameraMode":{"drawMode":0,"name":"Shaded","section":"Shading Mode"},"sceneLighting":true,"audioPlay":false,"sceneViewState":{"showFog":true,"showMaterialUpdate":false,"showSkybox":true,"showFlares":true,"showImageEffects":true,"showParticleSystems":true},"in2DMode":false,"pivot":{"x":0.5099999904632568,"y":2.680000066757202,"z":-1.3799999952316285},"rotation":{"x":0.0018095466075465084,"y":-0.010504195466637612,"z":0.00001910579521791078,"w":0.9999478459358215},"size":22.0,"orthographic":false}